yolov8/__init__.py
yolov8-0.0.2.dist-info/METADATA
yolov8-0.0.2.dist-info/WHEEL
yolov8-0.0.2.dist-info/top_level.txt
yolov8-0.0.2.dist-info/RECORD
